README.md
setup.cfg
setup.py
tpclientpy/__init__.py
tpclientpy/tradepatioclient.py
tpclientpy.egg-info/PKG-INFO
tpclientpy.egg-info/SOURCES.txt
tpclientpy.egg-info/dependency_links.txt
tpclientpy.egg-info/not-zip-safe
tpclientpy.egg-info/top_level.txt