Metadata-Version: 1.0
Name: tpclientpy
Version: 0.2
Summary: TradePatio client
Home-page: UNKNOWN
Author: UNKNOWN
Author-email: darkfoxs96@gmail.com
License: UNKNOWN
Platform: UNKNOWN
